bioevents-0.2.1.dist-info/METADATA
bioevents-0.2.1.dist-info/WHEEL
bioevents-0.2.1.dist-info/licenses/AUTHORS.rst
bioevents-0.2.1.dist-info/licenses/LICENSE
bioevents/.idea/.gitignore
bioevents/.idea/bioevents.iml
bioevents/.idea/inspectionProfiles/Project_Default.xml
bioevents/.idea/inspectionProfiles/profiles_settings.xml
bioevents/.idea/misc.xml
bioevents/.idea/modules.xml
bioevents/.idea/vcs.xml
bioevents/.idea/workspace.xml
bioevents/__init__.py
bioevents/colors.py
bioevents/event_handling.py
bioevents/hypnogram.py
bioevents-0.2.1.dist-info/RECORD
