Metadata-Version: 2.1
Name: bioevents
Version: 0.2.1
Summary: A lightweight library for managing and manipulating time series events, with a focus on biosensing applications.
Keywords: bioevents
Author-Email: McGregor Joyner <mcgsjoyner@gmail.com>
License: MIT license
Classifier: Development Status :: 2 - Pre-Alpha
Classifier: Intended Audience :: Developers
Classifier: License :: OSI Approved :: MIT License
Classifier: Natural Language :: English
Classifier: Programming Language :: Python :: 3
Classifier: Programming Language :: Python :: 3.9
Classifier: Programming Language :: Python :: 3.10
Classifier: Programming Language :: Python :: 3.11
Project-URL: Homepage, https://github.com/mcgsjoyner/bioevents
Requires-Python: >=3.9
Requires-Dist: setuptools>=68.2.0
Requires-Dist: matplotlib>=3.7.2
Requires-Dist: numpy>=1.24
Requires-Dist: pandas>=2
Requires-Dist: pydantic~=2.6
Requires-Dist: jupyter>=1.0.0; extra == "notebooks"
Provides-Extra: notebooks
